{
  "id": "documents_full:53510741-ed4e-4a81-9541-f528ea1e2632:48",
  "score": 0.4103,
  "source": "documents_full",
  "sourceId": "53510741-ed4e-4a81-9541-f528ea1e2632",
  "title": "Alchemy Long Term Venture Fund, Series 3 · Alchemy Long Term Ventures Fund, Series 3_Jan'26.pdf",
  "section": "Vehicle Document · AIF",
  "content": "in industry is provided herein above\n21\n\nGENERAL DISCLAIMER\nGeneral Risk Factors\n• All products / investment approach attract various kinds of risks. Please read the relevant Disclosure Document/ Client Agreement/ Offer Documents (includes Private Placement\nMemorandum and Contribution Agreement) carefully before investing.\nGeneral Disclaimers\n• The information and opinions contained in this report/ presentation have been obtained from sources believed to be reliable, but no representation or warranty, express or\nimplied, is made that such information is accurate or complete.\n• Information and opinions contained in the report/ presentation are disseminated for the information of authorized recipients only and are not to be relied upon as advisory or\nauthoritative or taken in substitution for the exercise of due diligence and judgement by any recipient.\n• The information and opinions are",
  "metadata": {
    "vehicleId": "baad99b8-5610-4225-91a8-2e2e25c9d7b6",
    "vehicleName": "Alchemy Long Term Venture Fund, Series 3",
    "vehicleType": "AIF",
    "fileType": "pdf",
    "fileName": "Alchemy Long Term Ventures Fund, Series 3_Jan'26.pdf",
    "fileSize": 975084,
    "ordinal": 48,
    "kind": "body"
  }
}