{
  "id": "documents_full:5e590c6e-b5a5-4169-990c-05cdb9b8e712:22",
  "score": 0.5305,
  "source": "documents_full",
  "sourceId": "5e590c6e-b5a5-4169-990c-05cdb9b8e712",
  "title": "ASK Core Fund · ASK CORE Fund Presentation_Deck(AIF).pdf",
  "section": "Vehicle Document · AIF",
  "content": "focused portfolio can Undervalued stocks Designed for investors Changes in economic\namplify both upside and may take longer to with 4-5 year horizon. conditions or policy\ndownside, especially reflect intrinsic value, frameworks can impact\nduring volatile phases requiring investor valuations and business\npatience fundamentals\n27\nRefer to Private Placement Memorandum (PPM) of the scheme before you make your decision to invest in this scheme offering",
  "metadata": {
    "vehicleId": "bc420a6c-76fa-4063-b5e1-ee1f52870dc8",
    "vehicleName": "ASK Core Fund",
    "vehicleType": "AIF",
    "fileType": "pdf",
    "fileName": "ASK CORE Fund Presentation_Deck(AIF).pdf",
    "fileSize": 2470603,
    "ordinal": 22,
    "kind": "body"
  }
}