{
  "id": "documents_full:c16c54bc-00cd-4cca-bb53-ea46098108b3:1",
  "score": 0.4068,
  "source": "documents_full",
  "sourceId": "c16c54bc-00cd-4cca-bb53-ea46098108b3",
  "title": "Aditya Birla Structured  Opportunities Fund Series 2 · ABSL Structured Opportunities Fund Series II_Deck.pdf",
  "section": "Vehicle Document · AIF",
  "content": "roduct\nor service.\nThe document is not for public distribution or advertisement, and no offer or solicitation to buy or sell securities is being made. The\ndetails herein are subject to change and do not constitute financial advice. Recipients should conduct their own due diligence and\nseek professional advice. Unauthorized use or distribution is prohibited.\nSecurity investments are subject to market risks and there is no assurance or guarantee that the investment objective will be achieved.\n2\n\nAgenda\nLeadership &\nIndicative\nMarket Mapping\nGovernance\nTerms\n1 3 5\n2 4\n6\nExecutive Investment\nDeals Done\nSummary Philosophy\n3\n\nExecutive Summary\n4",
  "metadata": {
    "vehicleId": "c9a9c7df-dfee-4fa5-b5e1-a2cbdcffd389",
    "vehicleName": "Aditya Birla Structured  Opportunities Fund Series 2",
    "vehicleType": "AIF",
    "fileType": "pdf",
    "fileName": "ABSL Structured Opportunities Fund Series II_Deck.pdf",
    "fileSize": 1331980,
    "ordinal": 1,
    "kind": "body"
  }
}